ecodev_cloud/__init__.py
ecodev_cloud/cloud/__init__.py
ecodev_cloud/cloud/blob/__init__.py
ecodev_cloud/cloud/blob/blob_container.py
ecodev_cloud/cloud/blob/blob_helpers.py
ecodev_cloud/cloud/cloud.py
ecodev_cloud/cloud/cloud_helpers.py
ecodev_cloud/cloud/cloud_loaders.py
ecodev_cloud/cloud/cloud_savers.py
ecodev_cloud/cloud/s3/__init__.py
ecodev_cloud/cloud/s3/s3_bucket.py
ecodev_cloud/cloud/s3/s3_helpers.py
ecodev_cloud/constants.py
ecodev_cloud/disk/__init__.py
ecodev_cloud/disk/disk_helpers.py
ecodev_cloud/disk/disk_loader.py
ecodev_cloud/disk/disk_saver.py
ecodev_cloud/file_processing/__init__.py
ecodev_cloud/file_processing/basic_file_processing.py
ecodev_cloud/file_processing/netcdf_processing.py
ecodev_cloud/file_processing/numpy_processing.py
ecodev_cloud/file_processing/shapely_processing.py
ecodev_cloud/file_processing/tif_processing.py
ecodev_cloud/path_utils.py
ecodev_cloud/transfer/__init__.py
ecodev_cloud/transfer/disk_to_blob.py
ecodev_cloud/transfer/migration_helpers.py
ecodev_cloud/transfer/s3_to_blob.py
ecodev_cloud-0.0.3.dist-info/LICENSE.md
ecodev_cloud-0.0.3.dist-info/METADATA
ecodev_cloud-0.0.3.dist-info/WHEEL
ecodev_cloud-0.0.3.dist-info/RECORD
